characterai_tts/__init__.py
characterai_tts/tts.py
characterai_tts-0.1.3.post1.dist-info/licenses/LICENSE
characterai_tts-0.1.3.post1.dist-info/METADATA
characterai_tts-0.1.3.post1.dist-info/WHEEL
characterai_tts-0.1.3.post1.dist-info/top_level.txt
characterai_tts-0.1.3.post1.dist-info/RECORD
