Metadata-Version: 2.4
Name: characterai-tts
Version: 0.1.3.post1
Summary: Uses Character AI for synthesis.
Home-page: https://github.com/davidsuragan/characterai-tts
Author: David Suragan
Author-email: davidsuragan@gmail.com
License: MIT
Classifier: Programming Language :: Python :: 3
Classifier: License :: OSI Approved :: MIT License
Classifier: Operating System :: OS Independent
Requires-Python: >=3.8
License-File: LICENSE
Requires-Dist: PyCharacterAI>=0.2.0
Requires-Dist: requests>=2.20.0
Requires-Dist: python-dotenv>=0.10.0
Provides-Extra: audio
Requires-Dist: pygame>=2.0.0; extra == "audio"
Dynamic: author
Dynamic: author-email
Dynamic: classifier
Dynamic: description
Dynamic: description-content-type
Dynamic: home-page
Dynamic: license
Dynamic: license-file
Dynamic: provides-extra
Dynamic: requires-dist
Dynamic: requires-python
Dynamic: summary
